myKGlib/__init__.py
myKGlib/chartdict.py
myKGlib/visualize.py
myKGlib/charts/__init__.py
myKGlib/charts/areachart.py
myKGlib/charts/barchart.py
myKGlib/charts/boxplot.py
myKGlib/charts/bubblechart.py
myKGlib/charts/chart.py
myKGlib/charts/densityplot.py
myKGlib/charts/dimensions.py
myKGlib/charts/donutchart.py
myKGlib/charts/graph.py
myKGlib/charts/heatmap.py
myKGlib/charts/histogram.py
myKGlib/charts/imagegrid.py
myKGlib/charts/linechart.py
myKGlib/charts/map.py
myKGlib/charts/piechart.py
myKGlib/charts/scatterchart.py
myKGlib/charts/stackedarechart.py
myKGlib/charts/sunburstchart.py
myKGlib/charts/table.py
myKGlib/charts/timeline.py
myKGlib/charts/tree.py
myKGlib/charts/treemaps.py
myKGlib/charts/violinplot.py
myKGlib/charts/wordcloud.py
myKGlib/utils/__init__.py
myKGlib/utils/util.py
myKGlib-0.0.0.9.dist-info/METADATA
myKGlib-0.0.0.9.dist-info/WHEEL
myKGlib-0.0.0.9.dist-info/top_level.txt
myKGlib-0.0.0.9.dist-info/RECORD
