Metadata-Version: 2.1
Name: myKGlib
Version: 0.0.0.9
Summary: demo
Home-page: UNKNOWN
Author: Hana
License: MIT
Platform: UNKNOWN
Requires-Dist: pandas (>=1.0.1)
Requires-Dist: SPARQLWrapper
Requires-Dist: matplotlib
Requires-Dist: seaborn
Requires-Dist: imageio
Requires-Dist: plotly (==4.14.3)
Requires-Dist: networkx
Requires-Dist: folium
Requires-Dist: anytree
Requires-Dist: wordcloud
Requires-Dist: IPython
